{
  "name": "学在浙大/智云课堂 辅助脚本",
  "description": "学在浙大/智云课堂 辅助脚本 by memset0",
  "namespace": "https://github.com/memset0/Learning-at-ZJU-Helper",
  "homepage": "https://github.com/memset0/Learning-at-ZJU-Helper",
  "supportURL": "https://github.com/memset0/Learning-at-ZJU-Helper/issues",
  "match": ["*://livingroom.cmc.zju.edu.cn/*", "*://onlineroom.cmc.zju.edu.cn/*", "*://classroom.zju.edu.cn/*", "*://interactivemeta.cmc.zju.edu.cn/*"],
  "grant": ["unsafeWindow", "GM_setValue", "GM_getValue", "GM_addValueChangeListener", "GM_removeValueChangeListener"],
  "require": [],
  "encoding": "utf-8",
  "run-at": "document-start",
  "downloadURL": "https://update.greasyfork.org/scripts/488869/%E5%AD%A6%E5%9C%A8%E6%B5%99%E5%A4%A7%E6%99%BA%E4%BA%91%E8%AF%BE%E5%A0%82%20%E8%BE%85%E5%8A%A9%E8%84%9A%E6%9C%AC.user.js",
  "updateURL": "https://update.greasyfork.org/scripts/488869/%E5%AD%A6%E5%9C%A8%E6%B5%99%E5%A4%A7%E6%99%BA%E4%BA%91%E8%AF%BE%E5%A0%82%20%E8%BE%85%E5%8A%A9%E8%84%9A%E6%9C%AC.meta.js"
}
